djangoldp_skill/__init__.py
djangoldp_skill/admin.py
djangoldp_skill/apps.py
djangoldp_skill/factories.py
djangoldp_skill/models.py
djangoldp_skill/settings.py
djangoldp_skill/translation.py
djangoldp_skill/management/__init__.py
djangoldp_skill/management/commands/__init__.py
djangoldp_skill/management/commands/mock_skill.py
djangoldp_skill/migrations/0001_initial.py
djangoldp_skill/migrations/0002_skill_urlid.py
djangoldp_skill/migrations/0003_auto_20200522_1516.py
djangoldp_skill/migrations/0004_auto_20200610_1323.py
djangoldp_skill/migrations/0005_auto_20200619_0813.py
djangoldp_skill/migrations/0006_auto_20201130_1147.py
djangoldp_skill/migrations/0007_auto_20210223_2254.py
djangoldp_skill/migrations/0008_skill_name_ar_dz_skill_name_ckb_skill_name_ig_and_more.py
djangoldp_skill/migrations/0009_alter_skill_urlid.py
djangoldp_skill/migrations/0010_add_timestamps_to_models.py
djangoldp_skill/migrations/0011_skill_name_ug.py
djangoldp_skill/migrations/__init__.py
djangoldp_skill-5.0.0.dist-info/METADATA
djangoldp_skill-5.0.0.dist-info/WHEEL
djangoldp_skill-5.0.0.dist-info/top_level.txt
djangoldp_skill-5.0.0.dist-info/RECORD
