Metadata-Version: 2.4
Name: djangoldp_skill
Version: 5.0.0
Summary: djangoldp package for skill data models
Home-page: http://git.happy-dev.fr/startinblox/djangoldp_skill
Author: Startin'blox
Author-email: nicolas@happy-dev.fr
License: MIT
Requires-Dist: djangoldp~=5.0.0
Requires-Dist: djangoldp_i18n
Provides-Extra: dev
Requires-Dist: factory_boy>=2.11.0; extra == "dev"
